flake8_github_actions/__init__.py
flake8_github_actions/py.typed
flake8_github_actions-0.1.1.dist-info/LICENSE
flake8_github_actions-0.1.1.dist-info/METADATA
flake8_github_actions-0.1.1.dist-info/WHEEL
flake8_github_actions-0.1.1.dist-info/entry_points.txt
flake8_github_actions-0.1.1.dist-info/top_level.txt
flake8_github_actions-0.1.1.dist-info/RECORD
