Metadata-Version: 2.1
Name: flake8-github-actions
Version: 0.1.1
Summary: GitHub Actions integration for flake8.
Home-page: https://github.com/domdfcoding/flake8-github-actions
Author: Dominic Davis-Foster
Author-email: dominic@davis-foster.co.uk
License: MIT License
Project-URL: Issue Tracker, https://github.com/domdfcoding/flake8-github-actions/issues
Project-URL: Source Code, https://github.com/domdfcoding/flake8-github-actions
Keywords: flake8,github,github-actions
Platform: Windows
Platform: macOS
Platform: Linux
Classifier: Environment :: Console
Classifier: Framework :: Flake8
Classifier: Intended Audience :: Developers
Classifier: License :: OSI Approved :: MIT License
Classifier: Operating System :: OS Independent
Classifier: Programming Language :: Python
Classifier: Programming Language :: Python :: 3 :: Only
Classifier: Programming Language :: Python :: 3.6
Classifier: Programming Language :: Python :: 3.7
Classifier: Programming Language :: Python :: 3.8
Classifier: Programming Language :: Python :: 3.9
Classifier: Programming Language :: Python :: Implementation :: CPython
Classifier: Programming Language :: Python :: Implementation :: PyPy
Classifier: Typing :: Typed
Requires-Python: >=3.6
Provides-Extra: all
